{"transpilation_time": 1.4707785401493312, "simulation_time": 0.03385474793612957, "gate_counts_before_transpilation": {"mcx_gray": 456, "x": 246, "barrier": 197, "h": 36, "ccx": 24, "u2": 5, "measure": 5, "u1": 3, "mcx": 3, "u3": 2}, "gate_counts_after_transpilation": {"mcx_gray": 456, "x": 208, "barrier": 197, "ccx": 24, "u2": 24, "h": 5, "measure": 5, "u1": 4, "z": 3, "mcx": 3, "u3": 2}, "circuit_depth_before_transpilation": 698, "circuit_depth_after_transpilation": 684, "qubit_count": 14, "num_grover_iterations": 3}